dgx/__init__.py
tapad_dgx-0.0.0.dist-info/LICENSE
tapad_dgx-0.0.0.dist-info/METADATA
tapad_dgx-0.0.0.dist-info/WHEEL
tapad_dgx-0.0.0.dist-info/top_level.txt
tapad_dgx-0.0.0.dist-info/RECORD
